sds/__init__.py
sds/delStr/__init__.py
sds/delStr/__init__.pyi
sds/pic/__init__.py
sds/str2e/__init__.py
sds/str2e/__init__.pyi
str_do_sth-1.0.0.dist-info/LICENSE
str_do_sth-1.0.0.dist-info/METADATA
str_do_sth-1.0.0.dist-info/WHEEL
str_do_sth-1.0.0.dist-info/top_level.txt
str_do_sth-1.0.0.dist-info/RECORD
