Metadata-Version: 2.1
Name: str-do-sth
Version: 1.0.0
Summary: it can take STR to INT,FLOAT,BOOL,LIST
Author: Cuber_AHZ
Author-email: 2119244804@qq.com
Classifier: Programming Language :: Python :: 3
Classifier: License :: OSI Approved :: MIT License
Classifier: Operating System :: OS Independent
License-File: LICENSE
